hello.py
helloyijuy-0.1.dist-info/METADATA
helloyijuy-0.1.dist-info/WHEEL
helloyijuy-0.1.dist-info/entry_points.txt
helloyijuy-0.1.dist-info/top_level.txt
helloyijuy-0.1.dist-info/RECORD
