Metadata-Version: 2.1
Name: helloyijuy
Version: 0.1
Requires-Dist: Click
